{
  "release-type": "node",
  "separate-pull-requests": true,
  "commit-batch-size": 1,
  "include-component-in-tag": true,
  "tag-separator": "-",
  "packages": {
    "handwritten/logging-winston": {
      "component": "logging-winston"
    },
    "handwritten/bigquery": {
      "component": "bigquery"
    },
    "handwritten/cloud-profiler": {
      "component": "cloud-profiler"
    },
    "handwritten/datastore": {
      "component": "datastore"
    },
    "handwritten/logging-bunyan": {
      "component": "logging-bunyan"
    }
  },
  "plugins": [
    {
      "type": "sentence-case"
    }
  ]
}
